cryptomatte_api-1.0.0.dist-info/RECORD
cryptomatte_api-1.0.0.dist-info/WHEEL
cryptomatte_api-1.0.0.dist-info/METADATA
cryptomatte_api-1.0.0.dist-info/licenses/LICENSE
cryptomatte_api/__init__.py
cryptomatte_api/py.typed
cryptomatte_api/include/pybind11_json/pybind11_json.hpp
cryptomatte_api/_stubs/__init__.pyi
cryptomatte_api/_stubs/_metadata.pyi
cryptomatte_api/_stubs/_manifest.pyi
cryptomatte_api/_stubs/_cryptomatte.pyi
cryptomatte_api/lib/cryptomatte_api.cpython-310-darwin.so
cryptomatte_api/share/cmake/pybind11_json/pybind11_jsonConfigVersion.cmake
cryptomatte_api/share/cmake/pybind11_json/pybind11_jsonConfig.cmake
cryptomatte_api/share/cmake/pybind11_json/pybind11_jsonTargets.cmake
