Metadata-Version: 2.2
Name: cryptomatte-api
Version: 1.0.0
Summary: A fast, memory-efficient and robust library for loading, validating and decoding cryptomattes.
Author-Email: Emil Dohne <emildohne@gmail.com>
Maintainer-Email: Emil Dohne <emildohne@gmail.com>
License: BSD-3-Clause
Project-URL: Homepage, https://cryptomatte-api.readthedocs.io/en/latest/
Project-URL: Source, https://github.com/EmilDohne/cryptomatte-api
Project-URL: Documentation, https://cryptomatte-api.readthedocs.io/en/latest/
Project-URL: Issues, https://github.com/EmilDohne/cryptomatte-api/issues
Requires-Python: >=3.9
Requires-Dist: numpy
Requires-Dist: compressed-image
